z3/__init__.py
z3/z3.py
z3/z3consts.py
z3/z3core.py
z3/z3num.py
z3/z3poly.py
z3/z3printer.py
z3/z3rcf.py
z3/z3types.py
z3/z3util.py
z3/include/z3++.h
z3/include/z3.h
z3/include/z3_algebraic.h
z3/include/z3_api.h
z3/include/z3_ast_containers.h
z3/include/z3_fixedpoint.h
z3/include/z3_fpa.h
z3/include/z3_macros.h
z3/include/z3_optimization.h
z3/include/z3_polynomial.h
z3/include/z3_rcf.h
z3/include/z3_spacer.h
z3/include/z3_v1.h
z3/include/z3_version.h
z3/lib/libz3.4.15.dylib
z3/lib/libz3.dll
z3/lib/libz3.dylib
z3/lib/msvcp140.dll
z3/lib/msvcp140_1.dll
z3/lib/msvcp140_2.dll
z3/lib/msvcp140_atomic_wait.dll
z3/lib/msvcp140_codecvt_ids.dll
z3/lib/vcomp140.dll
z3/lib/vcruntime140.dll
z3/lib/vcruntime140_1.dll
z3/lib/vcruntime140_threads.dll
z3_solver-4.15.0.0.data/data/bin/z3
z3_solver-4.15.0.0.dist-info/METADATA
z3_solver-4.15.0.0.dist-info/WHEEL
z3_solver-4.15.0.0.dist-info/top_level.txt
z3_solver-4.15.0.0.dist-info/RECORD
