Metadata-Version: 2.1
Name: z3-solver
Version: 4.15.0.0
Summary: an efficient SMT solver library
Home-page: https://github.com/Z3Prover/z3
Author: The Z3 Theorem Prover Project
Maintainer: Audrey Dutcher and Nikolaj Bjorner
Maintainer-email: audrey@rhelmot.io
License: MIT License
Keywords: z3,smt,sat,prover,theorem
Requires-Dist: importlib-resources ; python_version < "3.9"
